cluedin/README.md
cluedin/__init__.py
cluedin/account.py
cluedin/context.py
cluedin/entity.py
cluedin/env.py
cluedin/gql.py
cluedin/ingestion.py
cluedin/json.py
cluedin/jwt.py
cluedin/public.py
cluedin/rules/__init__.py
cluedin/rules/evaluator.py
cluedin/rules/operators.py
cluedin/rules/rule.py
cluedin/rules/rule_group.py
cluedin/rules/rules.py
cluedin/vocab.py
cluedin-3.0.0.dist-info/LICENSE
cluedin-3.0.0.dist-info/METADATA
cluedin-3.0.0.dist-info/WHEEL
cluedin-3.0.0.dist-info/RECORD
