Metadata-Version: 2.1
Name: cluedin
Version: 3.0.0
Summary: CluedIn Python SDK
Home-page: https://github.com/romaklimenko/cluedin
License: MIT
Keywords: cluedin,mdm,master data management
Author: Roman Klimenko
Author-email: roman@klimenko.dk
Maintainer: Roman Klimenko
Maintainer-email: roman@klimenko.dk
Requires-Python: >=3.10,<4.0
Classifier: License :: OSI Approved :: MIT License
Classifier: Programming Language :: Python :: 3
Classifier: Programming Language :: Python :: 3.10
Classifier: Programming Language :: Python :: 3.11
Classifier: Programming Language :: Python :: 3.12
Classifier: Programming Language :: Python :: 3.13
Requires-Dist: requests (>=2.32.3,<3.0.0)
Project-URL: Repository, https://github.com/romaklimenko/cluedin
